{
  "search_term": "바이오 그릭요거트 2입기획",
  "products": [
    {
      "prod_name": "매일유업바이오락토프리그릭요거트무가당 플레인 400g",
      "price": "3,220",
      "volume": "400g",
      "search_term": "바이오 그릭요거트 2입기획",
      "nutrition_info": {
        "칼로리": "101kcal",
        "단백질": "15g",
        "지방": "5g",
        "탄수화물": "9g",
        "당분": "11g",
        "나트륨": "51mg"
      }
    },
    {
      "prod_name": "매일유업바이오그릭요거트오리지널 플레인 80g",
      "price": "3,290",
      "volume": "80g",
      "search_term": "바이오 그릭요거트 2입기획",
      "nutrition_info": {
        "칼로리": "147kcal",
        "단백질": "12g",
        "지방": "7g",
        "탄수화물": "5g",
        "당분": "8g",
        "나트륨": "49mg"
      }
    },
    {
      "prod_name": "매일유업바이오그릭요거트플레인 800g",
      "price": "6,160",
      "volume": "800g",
      "search_term": "바이오 그릭요거트 2입기획",
      "nutrition_info": {
        "칼로리": "112kcal",
        "단백질": "12g",
        "지방": "8g",
        "탄수화물": "14g",
        "당분": "6g",
        "나트륨": "34mg"
      }
    }
  ],
  "timestamp": "2025-07-03 11:22:12"
}