{
  "selected_product": {
    "prod_name": "매일유업바이오락토프리그릭요거트무가당 플레인 400g",
    "price": "6,850",
    "volume": "400g",
    "search_term": "바이오 그릭요거트 2입 기획",
    "nutrition_info": {
      "칼로리": "118kcal",
      "단백질": "10g",
      "지방": "5g",
      "탄수화물": "11g",
      "당분": "1g",
      "나트륨": "74mg"
    }
  },
  "category": "매일 바이오 그릭요거트",
  "similar_products": [
    {
      "prod_name": "매일유업바이오락토프리그릭요거트무가당 플레인 400g",
      "price": "3,220",
      "volume": "400g",
      "category": "매일 바이오 그릭요거트",
      "nutrition": {
        "칼로리": "131kcal",
        "단백질": "15g",
        "지방": "1g",
        "탄수화물": "8g",
        "당분": "1g",
        "나트륨": "42mg"
      },
      "selected_volume_reference": "400g"
    },
    {
      "prod_name": "매일유업바이오그릭요거트오리지널 플레인 80g",
      "price": "3,290",
      "volume": "80g",
      "category": "매일 바이오 그릭요거트",
      "nutrition": {
        "칼로리": "126kcal",
        "단백질": "11g",
        "지방": "1g",
        "탄수화물": "6g",
        "당분": "5g",
        "나트륨": "55mg"
      },
      "selected_volume_reference": "400g"
    },
    {
      "prod_name": "매일유업바이오그릭요거트플레인 800g",
      "price": "6,010",
      "volume": "800g",
      "category": "매일 바이오 그릭요거트",
      "nutrition": {
        "칼로리": "145kcal",
        "단백질": "14g",
        "지방": "5g",
        "탄수화물": "12g",
        "당분": "5g",
        "나트륨": "46mg"
      },
      "selected_volume_reference": "400g"
    },
    {
      "prod_name": "매일유업바이오그릭요거트무가당 플레인 800g 2개",
      "price": "13,280",
      "volume": "800g",
      "category": "매일 바이오 그릭요거트",
      "nutrition": {
        "칼로리": "80kcal",
        "단백질": "12g",
        "지방": "3g",
        "탄수화물": "11g",
        "당분": "5g",
        "나트륨": "68mg"
      },
      "selected_volume_reference": "400g"
    },
    {
      "prod_name": "매일유업매일바이오그릭요거트to go 플레인 120g",
      "price": "1,550",
      "volume": "120g",
      "category": "매일 바이오 그릭요거트",
      "nutrition": {
        "칼로리": "131kcal",
        "단백질": "14g",
        "지방": "1g",
        "탄수화물": "6g",
        "당분": "2g",
        "나트륨": "55mg"
      },
      "selected_volume_reference": "400g"
    }
  ],
  "timestamp": "2025-07-03 15:12:24"
}